{"id": "0022500950", "date": "2026-03-11", "home": "DEN", "away": "HOU", "finalHome": 129, "finalAway": 93, "overtime": false, "nOvertimes": 0, "model": "PyTorch Neural Network", "timeline": [{"t": 0.0, "wp": 56.6, "hs": 0, "as": 0, "per": 1, "clock": "12:00", "play": "Start of 1st Period (10:14 PM EST)"}, {"t": 0.0, "wp": 56.6, "hs": 0, "as": 0, "per": 1, "clock": "12:00", "play": "Jump Ball Jokic vs. Sengun: Tip to Smith Jr."}, {"t": 0.45, "wp": 54.0, "hs": 0, "as": 2, "per": 1, "clock": "11:33", "play": "Sengun 6' Driving Layup (2 PTS) (Eason 1 AST)"}, {"t": 0.75, "wp": 57.0, "hs": 2, "as": 2, "per": 1, "clock": "11:15", "play": "Jokic 9' Turnaround Fadeaway (2 PTS)"}, {"t": 1.05, "wp": 53.4, "hs": 2, "as": 4, "per": 1, "clock": "10:57", "play": "Durant 10' Fadeaway Jumper (2 PTS)"}, {"t": 1.28, "wp": 53.6, "hs": 2, "as": 4, "per": 1, "clock": "10:43", "play": "MISS Johnson 25' 3PT Pullup Jump Shot"}, {"t": 1.35, "wp": 52.9, "hs": 2, "as": 4, "per": 1, "clock": "10:39", "play": "Eason REBOUND (Off:0 Def:1)"}, {"t": 1.45, "wp": 53.7, "hs": 2, "as": 4, "per": 1, "clock": "10:33", "play": "MISS Sengun 15' Pullup Jump Shot"}, {"t": 1.5, "wp": 53.4, "hs": 2, "as": 4, "per": 1, "clock": "10:30", "play": "Jokic REBOUND (Off:0 Def:1)"}, {"t": 1.58, "wp": 53.6, "hs": 2, "as": 4, "per": 1, "clock": "10:25", "play": "MISS Gordon 25' 3PT Running Jump Shot"}, {"t": 1.63, "wp": 53.0, "hs": 2, "as": 4, "per": 1, "clock": "10:22", "play": "Eason REBOUND (Off:0 Def:2)"}, {"t": 1.95, "wp": 55.2, "hs": 2, "as": 4, "per": 1, "clock": "10:03", "play": "MISS Smith Jr. 12' Step Back Jump Shot"}, {"t": 2.0, "wp": 53.1, "hs": 2, "as": 4, "per": 1, "clock": "10:00", "play": "Jokic REBOUND (Off:0 Def:2)"}, {"t": 2.2, "wp": 53.3, "hs": 2, "as": 4, "per": 1, "clock": "9:48", "play": "MISS Braun 25' 3PT Jump Shot"}, {"t": 2.27, "wp": 52.2, "hs": 2, "as": 4, "per": 1, "clock": "9:44", "play": "Smith Jr. REBOUND (Off:0 Def:1)"}, {"t": 2.45, "wp": 47.3, "hs": 2, "as": 7, "per": 1, "clock": "9:33", "play": "Smith Jr. 25' 3PT Jump Shot (3 PTS) (Sengun 1 AST)"}, {"t": 2.9, "wp": 43.0, "hs": 2, "as": 7, "per": 1, "clock": "9:06", "play": "MISS Murray 17' Pullup Jump Shot"}, {"t": 3.0, "wp": 44.9, "hs": 2, "as": 7, "per": 1, "clock": "9:00", "play": "Eason REBOUND (Off:0 Def:3)"}, {"t": 3.18, "wp": 45.9, "hs": 2, "as": 7, "per": 1, "clock": "8:49", "play": "Sengun Bad Pass Turnover (P1.T1)"}, {"t": 3.18, "wp": 42.9, "hs": 2, "as": 7, "per": 1, "clock": "8:49", "play": "Jokic STEAL (1 STL)"}, {"t": 3.28, "wp": 52.6, "hs": 4, "as": 7, "per": 1, "clock": "8:43", "play": "Braun 3' Running Layup (2 PTS) (Johnson 1 AST)"}, {"t": 3.58, "wp": 52.2, "hs": 4, "as": 7, "per": 1, "clock": "8:25", "play": "MISS Thompson 9' Driving Floating Jump Shot"}, {"t": 3.62, "wp": 50.8, "hs": 4, "as": 7, "per": 1, "clock": "8:23", "play": "Murray REBOUND (Off:0 Def:1)"}, {"t": 3.85, "wp": 54.2, "hs": 7, "as": 7, "per": 1, "clock": "8:09", "play": "Johnson 26' 3PT Jump Shot (3 PTS) (Jokic 1 AST)"}, {"t": 4.3, "wp": 55.0, "hs": 7, "as": 7, "per": 1, "clock": "7:42", "play": "MISS Thompson 25' 3PT Jump Shot"}, {"t": 4.33, "wp": 55.3, "hs": 7, "as": 7, "per": 1, "clock": "7:40", "play": "Johnson REBOUND (Off:0 Def:1)"}, {"t": 4.52, "wp": 57.2, "hs": 7, "as": 7, "per": 1, "clock": "7:29", "play": "Smith Jr. P.FOUL (P1.T1) (E.Scott)"}, {"t": 4.6, "wp": 66.0, "hs": 9, "as": 7, "per": 1, "clock": "7:24", "play": "Murray 1' Cutting Dunk Shot (2 PTS) (Jokic 2 AST)"}, {"t": 4.85, "wp": 66.1, "hs": 9, "as": 7, "per": 1, "clock": "7:09", "play": "NUGGETS T.Foul (Def. 3 Sec Jokic ) (C.Kirkland)"}, {"t": 4.85, "wp": 63.7, "hs": 9, "as": 8, "per": 1, "clock": "7:09", "play": "Durant Free Throw Technical (3 PTS)"}, {"t": 4.98, "wp": 63.9, "hs": 9, "as": 8, "per": 1, "clock": "7:01", "play": "Durant Bad Pass Turnover (P1.T2)"}, {"t": 4.98, "wp": 64.3, "hs": 9, "as": 8, "per": 1, "clock": "7:01", "play": "Murray STEAL (1 STL)"}, {"t": 5.05, "wp": 66.3, "hs": 11, "as": 8, "per": 1, "clock": "6:57", "play": "Murray 2' Running Layup (4 PTS)"}, {"t": 5.28, "wp": 67.2, "hs": 11, "as": 8, "per": 1, "clock": "6:43", "play": "MISS Eason 4' Driving Layup"}, {"t": 5.3, "wp": 62.9, "hs": 11, "as": 8, "per": 1, "clock": "6:42", "play": "Jokic REBOUND (Off:0 Def:3)"}, {"t": 5.55, "wp": 67.4, "hs": 11, "as": 8, "per": 1, "clock": "6:27", "play": "MISS Jokic 8' Turnaround Jump Shot"}, {"t": 5.62, "wp": 63.2, "hs": 11, "as": 8, "per": 1, "clock": "6:23", "play": "Eason REBOUND (Off:0 Def:4)"}, {"t": 5.72, "wp": 66.3, "hs": 11, "as": 8, "per": 1, "clock": "6:17", "play": "MISS Eason 26' 3PT Pullup Jump Shot"}, {"t": 5.75, "wp": 62.3, "hs": 11, "as": 8, "per": 1, "clock": "6:15", "play": "Eason REBOUND (Off:1 Def:4)"}, {"t": 5.8, "wp": 63.7, "hs": 11, "as": 10, "per": 1, "clock": "6:12", "play": "Smith Jr. 13' Pullup Jump Shot (5 PTS) (Eason 2 AST)"}, {"t": 6.08, "wp": 68.8, "hs": 14, "as": 10, "per": 1, "clock": "5:55", "play": "Murray 25' 3PT Jump Shot (7 PTS) (Jokic 3 AST)"}, {"t": 6.3, "wp": 70.8, "hs": 14, "as": 10, "per": 1, "clock": "5:42", "play": "MISS Thompson 10' Driving Floating Jump Shot"}, {"t": 6.3, "wp": 65.0, "hs": 14, "as": 10, "per": 1, "clock": "5:42", "play": "Jokic REBOUND (Off:0 Def:4)"}, {"t": 6.3, "wp": 66.5, "hs": 14, "as": 10, "per": 1, "clock": "5:42", "play": "Jokic Lost Ball Turnover (P1.T1)"}, {"t": 6.3, "wp": 65.0, "hs": 14, "as": 10, "per": 1, "clock": "5:42", "play": "Thompson STEAL (1 STL)"}, {"t": 6.3, "wp": 66.4, "hs": 14, "as": 10, "per": 1, "clock": "5:42", "play": "NUGGETS Timeout: Regular (Full 1 Short 0)"}, {"t": 6.3, "wp": 66.5, "hs": 14, "as": 10, "per": 1, "clock": "5:42", "play": "Instant Replay1st Period (10:25 PM EST)"}, {"t": 6.3, "wp": 66.4, "hs": 14, "as": 10, "per": 1, "clock": "5:42", "play": "SUB: Hardaway Jr. FOR Johnson"}, {"t": 6.3, "wp": 66.4, "hs": 14, "as": 10, "per": 1, "clock": "5:42", "play": "SUB: Okogie FOR Eason"}, {"t": 6.3, "wp": 70.8, "hs": 14, "as": 10, "per": 1, "clock": "5:42", "play": "SUB: Capela FOR Sengun"}, {"t": 6.3, "wp": 64.3, "hs": 14, "as": 10, "per": 1, "clock": "5:42", "play": "SUB: Sheppard FOR Thompson"}, {"t": 6.5, "wp": 68.9, "hs": 14, "as": 10, "per": 1, "clock": "5:30", "play": "MISS Okogie 25' 3PT Jump Shot"}, {"t": 6.53, "wp": 64.3, "hs": 14, "as": 10, "per": 1, "clock": "5:28", "play": "Capela REBOUND (Off:1 Def:0)"}, {"t": 6.55, "wp": 63.8, "hs": 14, "as": 10, "per": 1, "clock": "5:27", "play": "MISS Sheppard 26' 3PT Jump Shot"}, {"t": 6.57, "wp": 69.0, "hs": 14, "as": 10, "per": 1, "clock": "5:26", "play": "Okogie REBOUND (Off:1 Def:0)"}, {"t": 6.57, "wp": 61.7, "hs": 14, "as": 12, "per": 1, "clock": "5:26", "play": "Okogie Tip Dunk Shot (2 PTS)"}, {"t": 7.0, "wp": 64.8, "hs": 17, "as": 12, "per": 1, "clock": "5:00", "play": "Hardaway Jr. 25' 3PT Jump Shot (3 PTS) (Murray 1 AST)"}, {"t": 7.33, "wp": 61.9, "hs": 17, "as": 14, "per": 1, "clock": "4:40", "play": "Smith Jr. 13' Fadeaway Jumper (7 PTS)"}, {"t": 7.5, "wp": 64.6, "hs": 17, "as": 14, "per": 1, "clock": "4:30", "play": "MISS Murray 8' Driving Layup"}, {"t": 7.55, "wp": 62.5, "hs": 17, "as": 14, "per": 1, "clock": "4:27", "play": "Gordon REBOUND (Off:1 Def:0)"}, {"t": 7.55, "wp": 63.7, "hs": 17, "as": 14, "per": 1, "clock": "4:27", "play": "MISS Gordon Tip Layup Shot"}, {"t": 7.58, "wp": 63.5, "hs": 17, "as": 14, "per": 1, "clock": "4:25", "play": "Smith Jr. REBOUND (Off:0 Def:2)"}, {"t": 7.75, "wp": 64.2, "hs": 17, "as": 16, "per": 1, "clock": "4:15", "play": "Durant 3' Running Layup (5 PTS)"}, {"t": 7.9, "wp": 65.1, "hs": 17, "as": 16, "per": 1, "clock": "4:06", "play": "Jokic Bad Pass Turnover (P2.T2)"}, {"t": 7.9, "wp": 61.2, "hs": 17, "as": 16, "per": 1, "clock": "4:06", "play": "Sheppard STEAL (1 STL)"}, {"t": 7.97, "wp": 64.8, "hs": 17, "as": 16, "per": 1, "clock": "4:02", "play": "MISS Sheppard 27' 3PT Running Jump Shot"}, {"t": 8.02, "wp": 61.0, "hs": 17, "as": 16, "per": 1, "clock": "3:59", "play": "Gordon REBOUND (Off:1 Def:1)"}, {"t": 8.13, "wp": 62.8, "hs": 17, "as": 16, "per": 1, "clock": "3:52", "play": "MISS Gordon 27' 3PT Running Pull-Up Jump Shot"}, {"t": 8.17, "wp": 64.1, "hs": 17, "as": 16, "per": 1, "clock": "3:50", "play": "Durant REBOUND (Off:0 Def:1)"}, {"t": 8.33, "wp": 62.9, "hs": 17, "as": 16, "per": 1, "clock": "3:40", "play": "Sheppard Lost Ball Turnover (P1.T3)"}, {"t": 8.33, "wp": 64.5, "hs": 17, "as": 16, "per": 1, "clock": "3:40", "play": "Jokic STEAL (2 STL)"}, {"t": 8.37, "wp": 65.7, "hs": 17, "as": 16, "per": 1, "clock": "3:38", "play": "Jokic Lost Ball Turnover (P3.T3)"}, {"t": 8.37, "wp": 61.6, "hs": 17, "as": 16, "per": 1, "clock": "3:38", "play": "Sheppard STEAL (2 STL)"}, {"t": 8.5, "wp": 64.8, "hs": 17, "as": 16, "per": 1, "clock": "3:30", "play": "MISS Sheppard 24' 3PT Jump Shot"}, {"t": 8.58, "wp": 62.9, "hs": 17, "as": 16, "per": 1, "clock": "3:25", "play": "Gordon REBOUND (Off:1 Def:2)"}, {"t": 8.8, "wp": 64.3, "hs": 19, "as": 16, "per": 1, "clock": "3:12", "play": "Murray 14' Pullup Jump Shot (9 PTS) (Jokic 4 AST)"}, {"t": 9.08, "wp": 63.0, "hs": 19, "as": 18, "per": 1, "clock": "2:55", "play": "Smith Jr. 12' Jump Shot (9 PTS) (Durant 1 AST)"}, {"t": 9.08, "wp": 61.7, "hs": 19, "as": 18, "per": 1, "clock": "2:55", "play": "NUGGETS Timeout: Regular (Full 2 Short 0)"}, {"t": 9.08, "wp": 64.2, "hs": 19, "as": 18, "per": 1, "clock": "2:55", "play": "SUB: S. Jones FOR Murray"}, {"t": 9.08, "wp": 61.2, "hs": 19, "as": 18, "per": 1, "clock": "2:55", "play": "SUB: Brown FOR Gordon"}, {"t": 9.08, "wp": 61.1, "hs": 19, "as": 18, "per": 1, "clock": "2:55", "play": "SUB: Thompson FOR Durant"}, {"t": 9.08, "wp": 61.1, "hs": 19, "as": 18, "per": 1, "clock": "2:55", "play": "SUB: Eason FOR Smith Jr."}, {"t": 9.25, "wp": 61.0, "hs": 21, "as": 18, "per": 1, "clock": "2:45", "play": "Jokic 13' Jump Shot (4 PTS) (Brown 1 AST)"}, {"t": 9.68, "wp": 60.9, "hs": 21, "as": 20, "per": 1, "clock": "2:19", "play": "Eason 5' Jump Bank Shot (2 PTS)"}, {"t": 9.95, "wp": 62.3, "hs": 21, "as": 20, "per": 1, "clock": "2:03", "play": "MISS Jokic 25' 3PT Jump Shot"}, {"t": 10.0, "wp": 59.8, "hs": 21, "as": 20, "per": 1, "clock": "2:00", "play": "Eason REBOUND (Off:1 Def:5)"}, {"t": 10.12, "wp": 64.0, "hs": 21, "as": 20, "per": 1, "clock": "1:53", "play": "MISS Okogie 3PT Jump Shot"}, {"t": 10.18, "wp": 63.2, "hs": 21, "as": 20, "per": 1, "clock": "1:49", "play": "Jokic REBOUND (Off:0 Def:5)"}, {"t": 10.23, "wp": 65.4, "hs": 23, "as": 20, "per": 1, "clock": "1:46", "play": "Braun 1' Running Dunk (4 PTS) (Jokic 5 AST)"}, {"t": 10.68, "wp": 66.1, "hs": 23, "as": 20, "per": 1, "clock": "1:19", "play": "Rockets Turnover: Shot Clock (T#4)"}, {"t": 10.93, "wp": 68.0, "hs": 23, "as": 20, "per": 1, "clock": "1:04", "play": "MISS Hardaway Jr. 20' Pullup Jump Shot"}, {"t": 11.0, "wp": 65.4, "hs": 23, "as": 20, "per": 1, "clock": "1:00", "play": "Thompson REBOUND (Off:0 Def:1)"}, {"t": 11.12, "wp": 66.9, "hs": 23, "as": 20, "per": 1, "clock": "0:53", "play": "MISS Thompson 4' Driving Layup"}, {"t": 11.15, "wp": 65.0, "hs": 23, "as": 20, "per": 1, "clock": "0:51", "play": "Jokic REBOUND (Off:0 Def:6)"}, {"t": 11.52, "wp": 66.7, "hs": 23, "as": 20, "per": 1, "clock": "0:29", "play": "Jokic Bad Pass Turnover (P4.T4)"}, {"t": 11.52, "wp": 66.6, "hs": 23, "as": 20, "per": 1, "clock": "0:29", "play": "Eason STEAL (1 STL)"}, {"t": 11.87, "wp": 66.8, "hs": 23, "as": 20, "per": 1, "clock": "0:08", "play": "Sheppard Bad Pass Turnover (P2.T5)"}, {"t": 11.87, "wp": 66.7, "hs": 23, "as": 20, "per": 1, "clock": "0:08", "play": "Jokic STEAL (3 STL)"}, {"t": 11.93, "wp": 66.0, "hs": 23, "as": 20, "per": 1, "clock": "0:04", "play": "Okogie S.FOUL (P1.T2) (E.Scott)"}, {"t": 11.93, "wp": 69.7, "hs": 24, "as": 20, "per": 1, "clock": "0:04", "play": "Brown Free Throw 1 of 2 (1 PTS)"}, {"t": 11.93, "wp": 68.0, "hs": 24, "as": 20, "per": 1, "clock": "0:04", "play": "SUB: Sengun FOR Okogie"}, {"t": 11.93, "wp": 68.4, "hs": 24, "as": 20, "per": 1, "clock": "0:04", "play": "SUB: Durant FOR Capela"}, {"t": 11.93, "wp": 70.5, "hs": 24, "as": 20, "per": 1, "clock": "0:04", "play": "MISS Brown Free Throw 2 of 2"}, {"t": 11.97, "wp": 67.7, "hs": 24, "as": 20, "per": 1, "clock": "0:02", "play": "Thompson REBOUND (Off:0 Def:2)"}, {"t": 11.98, "wp": 69.7, "hs": 24, "as": 20, "per": 1, "clock": "0:01", "play": "Hardaway Jr. Personal Take Foul (P1.T1) (N.Sago)"}, {"t": 11.98, "wp": 68.3, "hs": 24, "as": 20, "per": 1, "clock": "0:01", "play": "SUB: Gordon FOR Jokic"}, {"t": 12.0, "wp": 69.7, "hs": 24, "as": 20, "per": 1, "clock": "0:00", "play": "Hardaway Jr. P.FOUL (P2.PN) (N.Sago)"}, {"t": 12.0, "wp": 70.8, "hs": 24, "as": 20, "per": 1, "clock": "0:00", "play": "MISS Sengun Free Throw 1 of 2"}, {"t": 12.0, "wp": 68.6, "hs": 24, "as": 20, "per": 1, "clock": "0:00", "play": "Rockets Rebound"}, {"t": 12.0, "wp": 67.8, "hs": 24, "as": 20, "per": 1, "clock": "0:00", "play": "SUB: Jokic FOR Gordon"}, {"t": 12.0, "wp": 69.6, "hs": 24, "as": 20, "per": 1, "clock": "0:00", "play": "MISS Sengun Free Throw 2 of 2"}, {"t": 12.0, "wp": 67.8, "hs": 24, "as": 20, "per": 1, "clock": "0:00", "play": "Rockets Rebound"}, {"t": 12.0, "wp": 67.8, "hs": 24, "as": 20, "per": 1, "clock": "0:00", "play": "End of 1st Period (10:39 PM EST)"}, {"t": 12.0, "wp": 65.5, "hs": 24, "as": 20, "per": 2, "clock": "12:00", "play": "Start of 2nd Period (10:42 PM EST)"}, {"t": 12.27, "wp": 70.3, "hs": 26, "as": 20, "per": 2, "clock": "11:44", "play": "Valanciunas 10' Fadeaway Jumper (2 PTS)"}, {"t": 12.6, "wp": 69.7, "hs": 26, "as": 22, "per": 2, "clock": "11:24", "play": "Sengun 3' Driving Layup (4 PTS) (Sheppard 1 AST)"}, {"t": 12.87, "wp": 70.0, "hs": 26, "as": 22, "per": 2, "clock": "11:08", "play": "MISS Murray 6' Driving Floating Jump Shot"}, {"t": 12.9, "wp": 64.4, "hs": 26, "as": 22, "per": 2, "clock": "11:06", "play": "Eason REBOUND (Off:1 Def:6)"}, {"t": 12.95, "wp": 70.0, "hs": 26, "as": 22, "per": 2, "clock": "11:03", "play": "MISS Smith Jr. 9' Running Pull-Up Jump Shot"}, {"t": 13.0, "wp": 64.3, "hs": 26, "as": 22, "per": 2, "clock": "11:00", "play": "Eason REBOUND (Off:2 Def:6)"}, {"t": 13.08, "wp": 66.3, "hs": 26, "as": 22, "per": 2, "clock": "10:55", "play": "Valanciunas S.FOUL (P1.T1) (C.Kirkland)"}, {"t": 13.08, "wp": 69.0, "hs": 26, "as": 22, "per": 2, "clock": "10:55", "play": "MISS Sengun Free Throw 1 of 2"}, {"t": 13.08, "wp": 65.9, "hs": 26, "as": 22, "per": 2, "clock": "10:55", "play": "Rockets Rebound"}, {"t": 13.08, "wp": 68.9, "hs": 26, "as": 22, "per": 2, "clock": "10:55", "play": "MISS Sengun Free Throw 2 of 2"}, {"t": 13.12, "wp": 62.8, "hs": 26, "as": 22, "per": 2, "clock": "10:53", "play": "S. Jones REBOUND (Off:0 Def:1)"}, {"t": 13.32, "wp": 75.8, "hs": 29, "as": 22, "per": 2, "clock": "10:41", "play": "Hardaway Jr. 27' 3PT Jump Shot (6 PTS) (Murray 2 AST)"}, {"t": 13.5, "wp": 71.3, "hs": 29, "as": 25, "per": 2, "clock": "10:30", "play": "Sheppard 26' 3PT Pullup Jump Shot (3 PTS)"}, {"t": 13.75, "wp": 74.4, "hs": 31, "as": 25, "per": 2, "clock": "10:15", "play": "Hardaway Jr. 2' Driving Layup (8 PTS) (Murray 3 AST)"}, {"t": 13.97, "wp": 74.6, "hs": 31, "as": 25, "per": 2, "clock": "10:02", "play": "MISS Smith Jr. 27' 3PT Jump Shot"}, {"t": 14.0, "wp": 72.0, "hs": 31, "as": 25, "per": 2, "clock": "10:00", "play": "Murray REBOUND (Off:0 Def:2)"}, {"t": 14.17, "wp": 73.0, "hs": 31, "as": 25, "per": 2, "clock": "9:50", "play": "MISS Hardaway Jr. 29' 3PT Jump Shot"}, {"t": 14.2, "wp": 69.9, "hs": 31, "as": 25, "per": 2, "clock": "9:48", "play": "Rockets Rebound"}, {"t": 14.4, "wp": 72.9, "hs": 31, "as": 25, "per": 2, "clock": "9:36", "play": "MISS Eason 24' 3PT Jump Shot"}, {"t": 14.47, "wp": 67.8, "hs": 31, "as": 25, "per": 2, "clock": "9:32", "play": "Hardaway Jr. REBOUND (Off:0 Def:1)"}, {"t": 14.53, "wp": 69.8, "hs": 31, "as": 25, "per": 2, "clock": "9:28", "play": "Hardaway Jr. Lost Ball Turnover (P1.T5)"}, {"t": 14.53, "wp": 70.5, "hs": 31, "as": 25, "per": 2, "clock": "9:28", "play": "Smith Jr. STEAL (1 STL)"}, {"t": 14.63, "wp": 71.1, "hs": 31, "as": 27, "per": 2, "clock": "9:22", "play": "Eason 3' Running Layup (4 PTS) (Smith Jr. 1 AST)"}, {"t": 14.95, "wp": 68.6, "hs": 31, "as": 27, "per": 2, "clock": "9:03", "play": "MISS Brown 27' 3PT Jump Shot"}, {"t": 14.98, "wp": 63.7, "hs": 31, "as": 27, "per": 2, "clock": "9:01", "play": "Smith Jr. REBOUND (Off:0 Def:3)"}, {"t": 15.1, "wp": 64.9, "hs": 31, "as": 29, "per": 2, "clock": "8:54", "play": "Thompson 3' Cutting Layup Shot (2 PTS) (Smith Jr. 2 AST)"}, {"t": 15.1, "wp": 64.3, "hs": 31, "as": 29, "per": 2, "clock": "8:54", "play": "Valanciunas S.FOUL (P2.T2) (E.Scott)"}, {"t": 15.1, "wp": 63.4, "hs": 31, "as": 29, "per": 2, "clock": "8:54", "play": "SUB: Johnson FOR Hardaway Jr."}, {"t": 15.1, "wp": 63.5, "hs": 31, "as": 29, "per": 2, "clock": "8:54", "play": "SUB: Durant FOR Eason"}, {"t": 15.1, "wp": 63.6, "hs": 31, "as": 29, "per": 2, "clock": "8:54", "play": "MISS Thompson Free Throw 1 of 1"}, {"t": 15.15, "wp": 61.1, "hs": 31, "as": 29, "per": 2, "clock": "8:51", "play": "Valanciunas REBOUND (Off:0 Def:1)"}, {"t": 15.33, "wp": 64.6, "hs": 31, "as": 29, "per": 2, "clock": "8:40", "play": "MISS Murray 16' Pullup Jump Shot"}, {"t": 15.38, "wp": 61.9, "hs": 31, "as": 29, "per": 2, "clock": "8:37", "play": "Thompson REBOUND (Off:0 Def:3)"}, {"t": 15.43, "wp": 59.2, "hs": 31, "as": 31, "per": 2, "clock": "8:34", "play": "Sengun 1' Running Dunk (6 PTS) (Thompson 1 AST)"}, {"t": 15.78, "wp": 63.4, "hs": 33, "as": 31, "per": 2, "clock": "8:13", "play": "Valanciunas 8' Jump Shot (4 PTS) (S. Jones 1 AST)"}, {"t": 16.08, "wp": 58.9, "hs": 33, "as": 33, "per": 2, "clock": "7:55", "play": "Sheppard 5' Driving Finger Roll Layup (5 PTS) (Durant 2 AST)"}, {"t": 16.32, "wp": 61.7, "hs": 35, "as": 33, "per": 2, "clock": "7:41", "play": "Murray 14' Fadeaway Jumper (11 PTS) (Valanciunas 1 AST)"}, {"t": 16.65, "wp": 58.2, "hs": 35, "as": 35, "per": 2, "clock": "7:21", "play": "Sengun 4' Turnaround Hook Shot (8 PTS) (Durant 3 AST)"}, {"t": 16.93, "wp": 63.4, "hs": 37, "as": 35, "per": 2, "clock": "7:04", "play": "Johnson 5' Driving Floating Jump Shot (5 PTS) (Valanciunas 2 AST)"}, {"t": 17.25, "wp": 57.5, "hs": 37, "as": 37, "per": 2, "clock": "6:45", "play": "Thompson 2' Alley Oop Dunk (4 PTS) (Sengun 2 AST)"}, {"t": 17.57, "wp": 56.2, "hs": 37, "as": 37, "per": 2, "clock": "6:26", "play": "Sheppard S.FOUL (P1.T1) (N.Sago)"}, {"t": 17.57, "wp": 56.3, "hs": 37, "as": 37, "per": 2, "clock": "6:26", "play": "NUGGETS Timeout: Regular (Full 3 Short 0)"}, {"t": 17.57, "wp": 56.7, "hs": 37, "as": 37, "per": 2, "clock": "6:26", "play": "SUB: Jokic FOR Valanciunas"}, {"t": 17.57, "wp": 57.6, "hs": 37, "as": 37, "per": 2, "clock": "6:26", "play": "SUB: Okogie FOR Thompson"}, {"t": 17.57, "wp": 58.0, "hs": 37, "as": 37, "per": 2, "clock": "6:26", "play": "MISS Murray Free Throw 1 of 2"}, {"t": 17.57, "wp": 57.6, "hs": 37, "as": 37, "per": 2, "clock": "6:26", "play": "NUGGETS Rebound"}, {"t": 17.57, "wp": 62.7, "hs": 38, "as": 37, "per": 2, "clock": "6:26", "play": "Murray Free Throw 2 of 2 (12 PTS)"}, {"t": 17.87, "wp": 62.6, "hs": 38, "as": 37, "per": 2, "clock": "6:08", "play": "Sheppard Bad Pass Turnover (P3.T6)"}, {"t": 17.87, "wp": 63.5, "hs": 38, "as": 37, "per": 2, "clock": "6:08", "play": "S. Jones STEAL (1 STL)"}, {"t": 17.95, "wp": 67.3, "hs": 38, "as": 37, "per": 2, "clock": "6:03", "play": "MISS S. Jones 4' Running Layup"}, {"t": 18.0, "wp": 63.5, "hs": 38, "as": 37, "per": 2, "clock": "6:00", "play": "Sheppard REBOUND (Off:0 Def:1)"}, {"t": 18.05, "wp": 66.7, "hs": 38, "as": 37, "per": 2, "clock": "5:57", "play": "MISS Durant 26' 3PT Running Jump Shot"}, {"t": 18.08, "wp": 64.1, "hs": 38, "as": 37, "per": 2, "clock": "5:55", "play": "Johnson REBOUND (Off:0 Def:2)"}, {"t": 18.17, "wp": 66.7, "hs": 38, "as": 37, "per": 2, "clock": "5:50", "play": "MISS Johnson 25' 3PT Running Jump Shot"}, {"t": 18.22, "wp": 64.7, "hs": 38, "as": 37, "per": 2, "clock": "5:47", "play": "NUGGETS Rebound"}, {"t": 18.22, "wp": 64.1, "hs": 38, "as": 37, "per": 2, "clock": "5:47", "play": "Smith Jr. L.B.FOUL (P2.T2) (C.Kirkland)"}, {"t": 18.32, "wp": 66.8, "hs": 40, "as": 37, "per": 2, "clock": "5:41", "play": "Murray 19' Step Back Jump Shot (14 PTS) (Jokic 6 AST)"}, {"t": 18.6, "wp": 64.0, "hs": 40, "as": 37, "per": 2, "clock": "5:24", "play": "SUB: Thompson FOR Sheppard"}, {"t": 18.6, "wp": 64.2, "hs": 40, "as": 37, "per": 2, "clock": "5:24", "play": "SUB: Gordon FOR S. Jones"}, {"t": 18.6, "wp": 64.1, "hs": 40, "as": 37, "per": 2, "clock": "5:24", "play": "SUB: Braun FOR Murray"}, {"t": 18.8, "wp": 64.5, "hs": 40, "as": 39, "per": 2, "clock": "5:12", "play": "Okogie 4' Driving Layup (4 PTS) (Thompson 2 AST)"}, {"t": 19.05, "wp": 66.2, "hs": 42, "as": 39, "per": 2, "clock": "4:57", "play": "Jokic 6' Floating Jump Shot (6 PTS) (Braun 1 AST)"}, {"t": 19.33, "wp": 64.4, "hs": 42, "as": 39, "per": 2, "clock": "4:40", "play": "Sengun 5 Second Violation Turnover (P2.T7)"}, {"t": 19.33, "wp": 63.9, "hs": 42, "as": 39, "per": 2, "clock": "4:40", "play": "SUB: Eason FOR Smith Jr."}, {"t": 19.5, "wp": 65.0, "hs": 42, "as": 39, "per": 2, "clock": "4:30", "play": "Jokic Offensive Charge Foul (P1) (N.Sago)"}, {"t": 19.5, "wp": 67.2, "hs": 42, "as": 39, "per": 2, "clock": "4:30", "play": "Jokic Offensive Foul Turnover (P5.T6)"}, {"t": 19.5, "wp": 63.7, "hs": 42, "as": 39, "per": 2, "clock": "4:30", "play": "SUB: Hardaway Jr. FOR Brown"}, {"t": 19.92, "wp": 64.5, "hs": 42, "as": 41, "per": 2, "clock": "4:05", "play": "Thompson 4' Layup (6 PTS) (Okogie 1 AST)"}, {"t": 20.23, "wp": 65.7, "hs": 42, "as": 41, "per": 2, "clock": "3:46", "play": "MISS Hardaway Jr. 6' Driving Layup"}, {"t": 20.23, "wp": 62.4, "hs": 42, "as": 41, "per": 2, "clock": "3:46", "play": "Jokic REBOUND (Off:1 Def:6)"}, {"t": 20.23, "wp": 67.5, "hs": 42, "as": 41, "per": 2, "clock": "3:46", "play": "MISS Jokic Tip Layup Shot"}, {"t": 20.23, "wp": 67.1, "hs": 42, "as": 41, "per": 2, "clock": "3:46", "play": "Okogie BLOCK (1 BLK)"}, {"t": 20.23, "wp": 63.5, "hs": 42, "as": 41, "per": 2, "clock": "3:46", "play": "Rockets Rebound"}, {"t": 20.5, "wp": 56.3, "hs": 42, "as": 43, "per": 2, "clock": "3:30", "play": "Thompson 2' Dunk (8 PTS) (Okogie 2 AST)"}, {"t": 20.95, "wp": 54.6, "hs": 42, "as": 43, "per": 2, "clock": "3:03", "play": "MISS Hardaway Jr. 25' 3PT Jump Shot"}, {"t": 20.98, "wp": 53.1, "hs": 42, "as": 43, "per": 2, "clock": "3:01", "play": "Durant REBOUND (Off:0 Def:2)"}, {"t": 21.08, "wp": 53.8, "hs": 42, "as": 43, "per": 2, "clock": "2:55", "play": "Thompson Bad Pass Turnover (P1.T8)"}, {"t": 21.08, "wp": 52.7, "hs": 42, "as": 43, "per": 2, "clock": "2:55", "play": "Jokic STEAL (4 STL)"}, {"t": 21.2, "wp": 64.0, "hs": 44, "as": 43, "per": 2, "clock": "2:48", "play": "Braun 1' Driving Layup (6 PTS) (Jokic 7 AST)"}, {"t": 21.5, "wp": 65.0, "hs": 44, "as": 43, "per": 2, "clock": "2:30", "play": "MISS Sengun 25' 3PT Jump Shot"}, {"t": 21.53, "wp": 62.6, "hs": 44, "as": 43, "per": 2, "clock": "2:28", "play": "Hardaway Jr. REBOUND (Off:0 Def:2)"}, {"t": 21.57, "wp": 67.1, "hs": 46, "as": 43, "per": 2, "clock": "2:26", "play": "Johnson 3' Running Layup (7 PTS) (Hardaway Jr. 1 AST)"}, {"t": 21.57, "wp": 66.2, "hs": 46, "as": 43, "per": 2, "clock": "2:26", "play": "Rockets Timeout: Regular (Reg.1 Short 0)"}, {"t": 21.57, "wp": 65.4, "hs": 46, "as": 43, "per": 2, "clock": "2:26", "play": "SUB: Murray FOR Johnson"}, {"t": 21.57, "wp": 65.6, "hs": 46, "as": 43, "per": 2, "clock": "2:26", "play": "SUB: Sheppard FOR Eason"}, {"t": 21.57, "wp": 65.4, "hs": 46, "as": 43, "per": 2, "clock": "2:26", "play": "SUB: Capela FOR Okogie"}, {"t": 21.57, "wp": 65.8, "hs": 46, "as": 43, "per": 2, "clock": "2:26", "play": "SUB: Smith Jr. FOR Sengun"}, {"t": 21.82, "wp": 67.7, "hs": 46, "as": 43, "per": 2, "clock": "2:11", "play": "Durant Bad Pass Turnover (P2.T9)"}, {"t": 21.82, "wp": 66.5, "hs": 46, "as": 43, "per": 2, "clock": "2:11", "play": "Braun STEAL (1 STL)"}, {"t": 21.88, "wp": 77.1, "hs": 48, "as": 43, "per": 2, "clock": "2:07", "play": "Braun 3' Running Layup (8 PTS) (Jokic 8 AST)"}, {"t": 22.28, "wp": 78.0, "hs": 48, "as": 43, "per": 2, "clock": "1:43", "play": "MISS Durant 18' Pullup Jump Shot"}, {"t": 22.35, "wp": 72.9, "hs": 48, "as": 43, "per": 2, "clock": "1:39", "play": "Capela REBOUND (Off:2 Def:0)"}, {"t": 22.43, "wp": 74.8, "hs": 48, "as": 43, "per": 2, "clock": "1:34", "play": "Capela Bad Pass Turnover (P1.T10)"}, {"t": 22.43, "wp": 74.5, "hs": 48, "as": 43, "per": 2, "clock": "1:34", "play": "Jokic STEAL (5 STL)"}, {"t": 22.53, "wp": 80.4, "hs": 50, "as": 43, "per": 2, "clock": "1:28", "play": "Braun 1' Running Layup (10 PTS) (Jokic 9 AST)"}, {"t": 22.88, "wp": 80.9, "hs": 50, "as": 43, "per": 2, "clock": "1:07", "play": "MISS Sheppard 27' 3PT Jump Shot"}, {"t": 22.97, "wp": 79.3, "hs": 50, "as": 43, "per": 2, "clock": "1:02", "play": "Smith Jr. REBOUND (Off:1 Def:3)"}, {"t": 23.02, "wp": 77.8, "hs": 50, "as": 45, "per": 2, "clock": "0:59", "play": "Capela Cutting Dunk Shot (2 PTS) (Thompson 3 AST)"}, {"t": 23.03, "wp": 75.6, "hs": 50, "as": 45, "per": 2, "clock": "0:58", "play": "Smith Jr. Personal Take Foul (P3.T3) (N.Sago)"}, {"t": 23.03, "wp": 71.7, "hs": 50, "as": 45, "per": 2, "clock": "0:58", "play": "SUB: Eason FOR Smith Jr."}, {"t": 23.33, "wp": 76.0, "hs": 50, "as": 45, "per": 2, "clock": "0:40", "play": "MISS Murray 7' Driving Floating Bank Jump Shot"}, {"t": 23.35, "wp": 69.9, "hs": 50, "as": 45, "per": 2, "clock": "0:39", "play": "Durant REBOUND (Off:0 Def:3)"}, {"t": 23.72, "wp": 73.5, "hs": 50, "as": 45, "per": 2, "clock": "0:17", "play": "Jokic P.FOUL (P2.T3) (E.Scott)"}, {"t": 23.72, "wp": 71.3, "hs": 50, "as": 45, "per": 2, "clock": "0:17", "play": "SUB: Sengun FOR Capela"}, {"t": 23.92, "wp": 66.6, "hs": 50, "as": 47, "per": 2, "clock": "0:05", "play": "Eason 5' Driving Layup (6 PTS) (Durant 4 AST)"}, {"t": 23.97, "wp": 76.8, "hs": 53, "as": 47, "per": 2, "clock": "0:02", "play": "Braun 31' 3PT Step Back Jump Shot (13 PTS) (Gordon 1 AST)"}, {"t": 24.0, "wp": 73.9, "hs": 53, "as": 47, "per": 2, "clock": "0:00", "play": "ROCKETS Heave"}, {"t": 24.0, "wp": 76.4, "hs": 53, "as": 47, "per": 2, "clock": "0:00", "play": "Rockets Rebound"}, {"t": 24.0, "wp": 76.1, "hs": 53, "as": 47, "per": 2, "clock": "0:00", "play": "End of 2nd Period (11:08 PM EST)"}, {"t": 24.0, "wp": 76.4, "hs": 53, "as": 47, "per": 3, "clock": "12:00", "play": "Start of 3rd Period (11:24 PM EST)"}, {"t": 24.17, "wp": 77.0, "hs": 53, "as": 47, "per": 3, "clock": "11:50", "play": "Durant P.FOUL (P1.T1) (N.Sago)"}, {"t": 24.35, "wp": 83.7, "hs": 55, "as": 47, "per": 3, "clock": "11:39", "play": "Jokic 10' Floating Jump Shot (8 PTS) (Braun 2 AST)"}, {"t": 24.65, "wp": 83.4, "hs": 55, "as": 47, "per": 3, "clock": "11:21", "play": "MISS Eason 25' 3PT Step Back Jump Shot"}, {"t": 24.7, "wp": 79.3, "hs": 55, "as": 47, "per": 3, "clock": "11:18", "play": "Braun REBOUND (Off:0 Def:1)"}, {"t": 24.8, "wp": 82.4, "hs": 55, "as": 47, "per": 3, "clock": "11:12", "play": "Durant S.FOUL (P2.T2) (C.Kirkland)"}, {"t": 24.8, "wp": 85.6, "hs": 56, "as": 47, "per": 3, "clock": "11:12", "play": "Jokic Free Throw 1 of 2 (9 PTS)"}, {"t": 24.8, "wp": 89.1, "hs": 57, "as": 47, "per": 3, "clock": "11:12", "play": "Jokic Free Throw 2 of 2 (10 PTS)"}, {"t": 25.0, "wp": 85.6, "hs": 57, "as": 49, "per": 3, "clock": "11:00", "play": "Thompson 3' Driving Layup (10 PTS)"}, {"t": 25.35, "wp": 84.6, "hs": 57, "as": 49, "per": 3, "clock": "10:39", "play": "MISS Murray 4' Driving Layup"}, {"t": 25.35, "wp": 85.6, "hs": 57, "as": 49, "per": 3, "clock": "10:39", "play": "Sengun BLOCK (1 BLK)"}, {"t": 25.38, "wp": 79.7, "hs": 57, "as": 49, "per": 3, "clock": "10:37", "play": "Durant REBOUND (Off:0 Def:4)"}, {"t": 25.45, "wp": 82.1, "hs": 57, "as": 51, "per": 3, "clock": "10:33", "play": "Eason 2' Running Layup (8 PTS) (Durant 5 AST)"}, {"t": 25.87, "wp": 80.5, "hs": 57, "as": 51, "per": 3, "clock": "10:08", "play": "MISS Braun 3' Driving Layup"}, {"t": 25.87, "wp": 81.9, "hs": 57, "as": 51, "per": 3, "clock": "10:08", "play": "Sengun BLOCK (2 BLK)"}, {"t": 25.92, "wp": 73.9, "hs": 57, "as": 51, "per": 3, "clock": "10:05", "play": "Sengun REBOUND (Off:0 Def:1)"}, {"t": 25.95, "wp": 80.1, "hs": 57, "as": 51, "per": 3, "clock": "10:03", "play": "MISS Durant 26' 3PT Running Pull-Up Jump Shot"}, {"t": 26.02, "wp": 73.2, "hs": 57, "as": 51, "per": 3, "clock": "9:59", "play": "Sengun REBOUND (Off:1 Def:1)"}, {"t": 26.07, "wp": 78.5, "hs": 57, "as": 53, "per": 3, "clock": "9:56", "play": "Durant 2' Cutting Dunk Shot (7 PTS) (Sengun 3 AST)"}, {"t": 26.32, "wp": 76.8, "hs": 57, "as": 53, "per": 3, "clock": "9:41", "play": "MISS Murray 20' Step Back Jump Shot"}, {"t": 26.4, "wp": 69.7, "hs": 57, "as": 53, "per": 3, "clock": "9:36", "play": "Smith Jr. REBOUND (Off:1 Def:4)"}, {"t": 26.53, "wp": 77.2, "hs": 57, "as": 53, "per": 3, "clock": "9:28", "play": "MISS Sengun 3' Cutting Dunk Shot"}, {"t": 26.53, "wp": 80.2, "hs": 57, "as": 53, "per": 3, "clock": "9:28", "play": "Gordon BLOCK (1 BLK)"}, {"t": 26.57, "wp": 70.5, "hs": 57, "as": 53, "per": 3, "clock": "9:26", "play": "Gordon REBOUND (Off:1 Def:3)"}, {"t": 26.67, "wp": 81.0, "hs": 60, "as": 53, "per": 3, "clock": "9:20", "play": "Johnson 3PT Running Jump Shot (10 PTS) (Jokic 10 AST)"}, {"t": 26.95, "wp": 80.4, "hs": 60, "as": 55, "per": 3, "clock": "9:03", "play": "Sengun 3' Driving Layup (10 PTS)"}, {"t": 27.02, "wp": 76.4, "hs": 60, "as": 55, "per": 3, "clock": "8:59", "play": "Sengun P.FOUL (P1.T3) (C.Kirkland)"}, {"t": 27.25, "wp": 79.1, "hs": 60, "as": 55, "per": 3, "clock": "8:45", "play": "MISS Jokic 26' 3PT Jump Shot"}, {"t": 27.32, "wp": 74.4, "hs": 60, "as": 55, "per": 3, "clock": "8:41", "play": "Thompson REBOUND (Off:0 Def:4)"}, {"t": 27.38, "wp": 84.1, "hs": 60, "as": 55, "per": 3, "clock": "8:37", "play": "MISS Thompson 2' Running Layup"}, {"t": 27.38, "wp": 83.7, "hs": 60, "as": 55, "per": 3, "clock": "8:37", "play": "Jokic BLOCK (1 BLK)"}, {"t": 27.38, "wp": 79.4, "hs": 60, "as": 55, "per": 3, "clock": "8:37", "play": "NUGGETS Rebound"}, {"t": 27.57, "wp": 86.8, "hs": 62, "as": 55, "per": 3, "clock": "8:26", "play": "Jokic 5' Floating Jump Shot (12 PTS) (Johnson 2 AST)"}, {"t": 27.98, "wp": 83.8, "hs": 62, "as": 55, "per": 3, "clock": "8:01", "play": "MISS Eason 26' 3PT Jump Shot"}, {"t": 28.03, "wp": 84.3, "hs": 62, "as": 55, "per": 3, "clock": "7:58", "play": "Braun REBOUND (Off:0 Def:2)"}, {"t": 28.08, "wp": 86.0, "hs": 64, "as": 55, "per": 3, "clock": "7:55", "play": "Murray 1' Running Dunk (16 PTS) (Braun 3 AST)"}, {"t": 28.08, "wp": 82.5, "hs": 64, "as": 55, "per": 3, "clock": "7:55", "play": "Rockets Timeout: Regular (Reg.2 Short 0)"}, {"t": 28.08, "wp": 87.0, "hs": 64, "as": 55, "per": 3, "clock": "7:55", "play": "SUB: Sheppard FOR Eason"}, {"t": 28.37, "wp": 90.4, "hs": 64, "as": 55, "per": 3, "clock": "7:38", "play": "MISS Sheppard 26' 3PT Jump Shot"}, {"t": 28.4, "wp": 87.1, "hs": 64, "as": 55, "per": 3, "clock": "7:36", "play": "Braun REBOUND (Off:0 Def:3)"}, {"t": 28.47, "wp": 89.4, "hs": 64, "as": 55, "per": 3, "clock": "7:32", "play": "MISS Murray 3' Running Layup"}, {"t": 28.47, "wp": 90.1, "hs": 64, "as": 55, "per": 3, "clock": "7:32", "play": "Sengun BLOCK (3 BLK)"}, {"t": 28.5, "wp": 85.7, "hs": 64, "as": 55, "per": 3, "clock": "7:30", "play": "Jokic REBOUND (Off:2 Def:6)"}, {"t": 28.67, "wp": 93.2, "hs": 67, "as": 55, "per": 3, "clock": "7:20", "play": "Johnson 25' 3PT Jump Shot (13 PTS) (Jokic 11 AST)"}, {"t": 28.88, "wp": 91.9, "hs": 67, "as": 57, "per": 3, "clock": "7:07", "play": "Durant 14' Pullup Jump Shot (9 PTS) (Thompson 4 AST)"}, {"t": 29.22, "wp": 91.7, "hs": 67, "as": 57, "per": 3, "clock": "6:47", "play": "MISS Jokic 12' Jump Shot"}, {"t": 29.27, "wp": 89.6, "hs": 67, "as": 57, "per": 3, "clock": "6:44", "play": "Smith Jr. REBOUND (Off:1 Def:5)"}, {"t": 29.38, "wp": 87.1, "hs": 67, "as": 59, "per": 3, "clock": "6:37", "play": "Thompson 9' Pullup Jump Shot (12 PTS)"}, {"t": 29.52, "wp": 90.3, "hs": 69, "as": 59, "per": 3, "clock": "6:29", "play": "Jokic 3' Driving Layup (14 PTS)"}, {"t": 29.52, "wp": 90.6, "hs": 69, "as": 59, "per": 3, "clock": "6:29", "play": "Sengun S.FOUL (P2.T4) (N.Sago)"}, {"t": 29.52, "wp": 92.3, "hs": 70, "as": 59, "per": 3, "clock": "6:29", "play": "Jokic Free Throw 1 of 1 (15 PTS)"}, {"t": 29.83, "wp": 88.3, "hs": 70, "as": 61, "per": 3, "clock": "6:10", "play": "Smith Jr. 9' Pullup Jump Shot (11 PTS) (Sheppard 2 AST)"}, {"t": 30.02, "wp": 86.3, "hs": 70, "as": 61, "per": 3, "clock": "5:59", "play": "Smith Jr. P.FOUL (P4.PN) (E.Scott)"}, {"t": 30.02, "wp": 91.3, "hs": 71, "as": 61, "per": 3, "clock": "5:59", "play": "Murray Free Throw 1 of 2 (17 PTS)"}, {"t": 30.02, "wp": 90.3, "hs": 71, "as": 61, "per": 3, "clock": "5:59", "play": "SUB: Eason FOR Thompson"}, {"t": 30.02, "wp": 90.4, "hs": 71, "as": 61, "per": 3, "clock": "5:59", "play": "SUB: Okogie FOR Smith Jr."}, {"t": 30.02, "wp": 92.6, "hs": 72, "as": 61, "per": 3, "clock": "5:59", "play": "Murray Free Throw 2 of 2 (18 PTS)"}, {"t": 30.27, "wp": 92.4, "hs": 72, "as": 61, "per": 3, "clock": "5:44", "play": "Eason Bad Pass Turnover (P1.T11)"}, {"t": 30.27, "wp": 92.7, "hs": 72, "as": 61, "per": 3, "clock": "5:44", "play": "Johnson STEAL (1 STL)"}, {"t": 30.35, "wp": 92.9, "hs": 72, "as": 61, "per": 3, "clock": "5:39", "play": "Okogie S.FOUL (P2.PN) (N.Sago)"}, {"t": 30.35, "wp": 94.0, "hs": 73, "as": 61, "per": 3, "clock": "5:39", "play": "Johnson Free Throw 1 of 2 (14 PTS)"}, {"t": 30.35, "wp": 95.3, "hs": 74, "as": 61, "per": 3, "clock": "5:39", "play": "Johnson Free Throw 2 of 2 (15 PTS)"}, {"t": 30.67, "wp": 95.1, "hs": 74, "as": 61, "per": 3, "clock": "5:20", "play": "Durant Bad Pass Turnover (P3.T12)"}, {"t": 30.67, "wp": 95.2, "hs": 74, "as": 61, "per": 3, "clock": "5:20", "play": "Johnson STEAL (2 STL)"}, {"t": 30.77, "wp": 96.6, "hs": 76, "as": 61, "per": 3, "clock": "5:14", "play": "Murray 2' Running Layup (20 PTS)"}, {"t": 31.18, "wp": 96.2, "hs": 76, "as": 63, "per": 3, "clock": "4:49", "play": "Durant 12' Pullup Jump Shot (11 PTS)"}, {"t": 31.38, "wp": 96.2, "hs": 76, "as": 63, "per": 3, "clock": "4:37", "play": "MISS Murray 14' Turnaround Jump Shot"}, {"t": 31.42, "wp": 94.6, "hs": 76, "as": 63, "per": 3, "clock": "4:35", "play": "Jokic REBOUND (Off:3 Def:6)"}, {"t": 31.45, "wp": 97.1, "hs": 79, "as": 63, "per": 3, "clock": "4:33", "play": "Braun 24' 3PT Jump Shot (16 PTS) (Johnson 3 AST)"}, {"t": 31.72, "wp": 98.0, "hs": 79, "as": 63, "per": 3, "clock": "4:17", "play": "MISS Sheppard 25' 3PT Pullup Jump Shot"}, {"t": 31.77, "wp": 97.0, "hs": 79, "as": 63, "per": 3, "clock": "4:14", "play": "Jokic REBOUND (Off:3 Def:7)"}, {"t": 31.95, "wp": 98.4, "hs": 82, "as": 63, "per": 3, "clock": "4:03", "play": "Braun 26' 3PT Jump Shot (19 PTS) (Johnson 4 AST)"}, {"t": 31.98, "wp": 98.4, "hs": 82, "as": 63, "per": 3, "clock": "4:01", "play": "Rockets Timeout: Regular (Reg.3 Short 0)"}, {"t": 31.98, "wp": 98.6, "hs": 82, "as": 63, "per": 3, "clock": "4:01", "play": "SUB: S. Jones FOR Gordon"}, {"t": 31.98, "wp": 98.6, "hs": 82, "as": 63, "per": 3, "clock": "4:01", "play": "SUB: Thompson FOR Durant"}, {"t": 31.98, "wp": 98.7, "hs": 82, "as": 63, "per": 3, "clock": "4:01", "play": "SUB: Holiday FOR Sengun"}, {"t": 31.98, "wp": 98.8, "hs": 82, "as": 63, "per": 3, "clock": "4:01", "play": "SUB: Smith Jr. FOR Eason"}, {"t": 31.98, "wp": 98.8, "hs": 82, "as": 63, "per": 3, "clock": "4:01", "play": "SUB: Capela FOR Okogie"}, {"t": 32.28, "wp": 99.1, "hs": 82, "as": 63, "per": 3, "clock": "3:43", "play": "MISS Holiday 28' 3PT Jump Shot"}, {"t": 32.32, "wp": 98.6, "hs": 82, "as": 63, "per": 3, "clock": "3:41", "play": "Braun REBOUND (Off:0 Def:4)"}, {"t": 32.42, "wp": 99.1, "hs": 82, "as": 63, "per": 3, "clock": "3:35", "play": "MISS S. Jones 3' Running Dunk"}, {"t": 32.42, "wp": 98.8, "hs": 82, "as": 63, "per": 3, "clock": "3:35", "play": "Capela BLOCK (1 BLK)"}, {"t": 32.45, "wp": 98.7, "hs": 82, "as": 63, "per": 3, "clock": "3:33", "play": "Sheppard REBOUND (Off:0 Def:2)"}, {"t": 32.5, "wp": 98.7, "hs": 82, "as": 65, "per": 3, "clock": "3:30", "play": "Sheppard 4' Running Layup (7 PTS)"}, {"t": 32.7, "wp": 98.5, "hs": 82, "as": 65, "per": 3, "clock": "3:18", "play": "Thompson S.FOUL (P1.PN) (C.Kirkland)"}, {"t": 32.7, "wp": 98.7, "hs": 83, "as": 65, "per": 3, "clock": "3:18", "play": "Murray Free Throw 1 of 2 (21 PTS)"}, {"t": 32.7, "wp": 98.6, "hs": 83, "as": 65, "per": 3, "clock": "3:18", "play": "SUB: Hardaway Jr. FOR Braun"}, {"t": 32.7, "wp": 99.0, "hs": 84, "as": 65, "per": 3, "clock": "3:18", "play": "Murray Free Throw 2 of 2 (22 PTS)"}, {"t": 32.83, "wp": 99.0, "hs": 84, "as": 65, "per": 3, "clock": "3:10", "play": "S. Jones P.FOUL (P1.T1) (C.Kirkland)"}, {"t": 32.83, "wp": 98.8, "hs": 84, "as": 65, "per": 3, "clock": "3:10", "play": "SUB: Brown FOR Murray"}, {"t": 32.97, "wp": 99.1, "hs": 84, "as": 65, "per": 3, "clock": "3:02", "play": "MISS Smith Jr. 15' Pullup Jump Shot"}, {"t": 32.97, "wp": 98.8, "hs": 84, "as": 65, "per": 3, "clock": "3:02", "play": "Johnson BLOCK (1 BLK)"}, {"t": 33.0, "wp": 98.9, "hs": 84, "as": 65, "per": 3, "clock": "3:00", "play": "Rockets Rebound"}, {"t": 33.0, "wp": 99.1, "hs": 84, "as": 65, "per": 3, "clock": "3:00", "play": "Hardaway Jr. L.B.FOUL (P3.T2) (N.Sago)"}, {"t": 33.12, "wp": 99.2, "hs": 84, "as": 65, "per": 3, "clock": "2:53", "play": "MISS Smith Jr. 11' Driving Floating Jump Shot"}, {"t": 33.12, "wp": 98.9, "hs": 84, "as": 65, "per": 3, "clock": "2:53", "play": "Johnson BLOCK (2 BLK)"}, {"t": 33.17, "wp": 98.8, "hs": 84, "as": 65, "per": 3, "clock": "2:50", "play": "S. Jones REBOUND (Off:0 Def:2)"}, {"t": 33.17, "wp": 99.1, "hs": 84, "as": 65, "per": 3, "clock": "2:50", "play": "Sheppard S.FOUL (P2.PN) (E.Scott)"}, {"t": 33.17, "wp": 99.1, "hs": 84, "as": 65, "per": 3, "clock": "2:50", "play": "MISS Brown Free Throw 1 of 2"}, {"t": 33.17, "wp": 98.9, "hs": 84, "as": 65, "per": 3, "clock": "2:50", "play": "NUGGETS Rebound"}, {"t": 33.17, "wp": 98.5, "hs": 85, "as": 65, "per": 3, "clock": "2:50", "play": "Brown Free Throw 2 of 2 (2 PTS)"}, {"t": 33.4, "wp": 99.1, "hs": 85, "as": 67, "per": 3, "clock": "2:36", "play": "Thompson 5' Driving Floating Bank Jump Shot (14 PTS)"}, {"t": 33.65, "wp": 98.4, "hs": 87, "as": 67, "per": 3, "clock": "2:21", "play": "Johnson 10' Pullup Jump Shot (17 PTS) (Jokic 12 AST)"}, {"t": 34.12, "wp": 98.7, "hs": 87, "as": 67, "per": 3, "clock": "1:53", "play": "MISS Holiday 7' Driving Floating Bank Jump Shot"}, {"t": 34.15, "wp": 98.3, "hs": 87, "as": 67, "per": 3, "clock": "1:51", "play": "Jokic REBOUND (Off:3 Def:8)"}, {"t": 34.22, "wp": 98.8, "hs": 87, "as": 67, "per": 3, "clock": "1:47", "play": "MISS Brown 6' Running Layup"}, {"t": 34.22, "wp": 98.4, "hs": 87, "as": 67, "per": 3, "clock": "1:47", "play": "Sheppard BLOCK (1 BLK)"}, {"t": 34.22, "wp": 98.4, "hs": 87, "as": 67, "per": 3, "clock": "1:47", "play": "Rockets Rebound"}, {"t": 34.5, "wp": 98.8, "hs": 87, "as": 67, "per": 3, "clock": "1:30", "play": "MISS Thompson 6' Driving Floating Bank Jump Shot"}, {"t": 34.53, "wp": 98.3, "hs": 87, "as": 67, "per": 3, "clock": "1:28", "play": "Thompson REBOUND (Off:1 Def:4)"}, {"t": 34.53, "wp": 99.2, "hs": 87, "as": 69, "per": 3, "clock": "1:28", "play": "Thompson Putback Dunk (16 PTS)"}, {"t": 34.87, "wp": 99.1, "hs": 87, "as": 69, "per": 3, "clock": "1:08", "play": "MISS Johnson 6' Driving Finger Roll Layup"}, {"t": 34.92, "wp": 98.8, "hs": 87, "as": 69, "per": 3, "clock": "1:05", "play": "Jokic REBOUND (Off:4 Def:8)"}, {"t": 34.95, "wp": 99.1, "hs": 87, "as": 69, "per": 3, "clock": "1:03", "play": "MISS Jokic 8' Hook Shot"}, {"t": 34.98, "wp": 98.8, "hs": 87, "as": 69, "per": 3, "clock": "1:01", "play": "Smith Jr. REBOUND (Off:1 Def:6)"}, {"t": 35.0, "wp": 98.9, "hs": 87, "as": 69, "per": 3, "clock": "1:00", "play": "Smith Jr. Out of Bounds - Bad Pass Turnover Turnover (P1.T13)"}, {"t": 35.13, "wp": 99.1, "hs": 87, "as": 69, "per": 3, "clock": "0:52", "play": " Foul : Double Personal - Thompson (2 PF), Johnson (1 PF) (E.Scott)"}, {"t": 35.32, "wp": 99.1, "hs": 87, "as": 69, "per": 3, "clock": "0:41", "play": "Capela S.FOUL (P1.PN) (C.Kirkland)"}, {"t": 35.32, "wp": 99.1, "hs": 87, "as": 69, "per": 3, "clock": "0:41", "play": "MISS Jokic Free Throw 1 of 2"}, {"t": 35.32, "wp": 99.0, "hs": 87, "as": 69, "per": 3, "clock": "0:41", "play": "NUGGETS Rebound"}, {"t": 35.32, "wp": 99.2, "hs": 88, "as": 69, "per": 3, "clock": "0:41", "play": "Jokic Free Throw 2 of 2 (16 PTS)"}, {"t": 35.4, "wp": 99.2, "hs": 88, "as": 69, "per": 3, "clock": "0:36", "play": "Thompson Bad Pass Turnover (P2.T14)"}, {"t": 35.4, "wp": 99.2, "hs": 88, "as": 69, "per": 3, "clock": "0:36", "play": "S. Jones STEAL (2 STL)"}, {"t": 35.48, "wp": 99.0, "hs": 90, "as": 69, "per": 3, "clock": "0:31", "play": "Brown 2' Running Dunk (4 PTS) (S. Jones 2 AST)"}, {"t": 35.63, "wp": 99.2, "hs": 90, "as": 69, "per": 3, "clock": "0:22", "play": "MISS Sheppard 27' 3PT Jump Shot"}, {"t": 35.65, "wp": 98.9, "hs": 90, "as": 69, "per": 3, "clock": "0:21", "play": "Hardaway Jr. REBOUND (Off:0 Def:3)"}, {"t": 35.93, "wp": 99.4, "hs": 93, "as": 69, "per": 3, "clock": "0:04", "play": "Hardaway Jr. 25' 3PT Jump Shot (11 PTS) (Jokic 13 AST)"}, {"t": 36.0, "wp": 99.6, "hs": 93, "as": 69, "per": 3, "clock": "0:00", "play": "MISS Holiday 36' 3PT Jump Shot"}, {"t": 36.0, "wp": 99.5, "hs": 93, "as": 69, "per": 3, "clock": "0:00", "play": "Rockets Rebound"}, {"t": 36.0, "wp": 99.5, "hs": 93, "as": 69, "per": 3, "clock": "0:00", "play": "End of 3rd Period (11:54 PM EST)"}, {"t": 36.0, "wp": 99.7, "hs": 93, "as": 69, "per": 4, "clock": "12:00", "play": "Start of 4th Period (11:57 PM EST)"}, {"t": 36.32, "wp": 99.8, "hs": 93, "as": 69, "per": 4, "clock": "11:41", "play": "MISS Okogie 6' Driving Hook Shot"}, {"t": 36.35, "wp": 99.7, "hs": 93, "as": 69, "per": 4, "clock": "11:39", "play": "Valanciunas REBOUND (Off:0 Def:2)"}, {"t": 36.5, "wp": 99.8, "hs": 93, "as": 69, "per": 4, "clock": "11:30", "play": "Brown Bad Pass Turnover (P1.T7)"}, {"t": 36.5, "wp": 99.7, "hs": 93, "as": 69, "per": 4, "clock": "11:30", "play": "Capela STEAL (1 STL)"}, {"t": 36.6, "wp": 99.8, "hs": 93, "as": 69, "per": 4, "clock": "11:24", "play": "Valanciunas S.FOUL (P3.T1) (C.Kirkland)"}, {"t": 36.6, "wp": 99.8, "hs": 93, "as": 69, "per": 4, "clock": "11:24", "play": "MISS Okogie Free Throw 1 of 2"}, {"t": 36.6, "wp": 99.8, "hs": 93, "as": 69, "per": 4, "clock": "11:24", "play": "Rockets Rebound"}, {"t": 36.6, "wp": 99.8, "hs": 93, "as": 69, "per": 4, "clock": "11:24", "play": "MISS Okogie Free Throw 2 of 2"}, {"t": 36.63, "wp": 99.8, "hs": 93, "as": 69, "per": 4, "clock": "11:22", "play": "NUGGETS Rebound"}, {"t": 36.85, "wp": 99.9, "hs": 96, "as": 69, "per": 4, "clock": "11:09", "play": "Hardaway Jr. 26' 3PT Jump Shot (14 PTS) (Brown 2 AST)"}, {"t": 37.13, "wp": 99.9, "hs": 96, "as": 71, "per": 4, "clock": "10:52", "play": "Sheppard 8' Driving Finger Roll Layup (9 PTS)"}, {"t": 37.5, "wp": 99.8, "hs": 96, "as": 71, "per": 4, "clock": "10:30", "play": "Murray Lost Ball Turnover (P1.T8)"}, {"t": 37.5, "wp": 99.8, "hs": 96, "as": 71, "per": 4, "clock": "10:30", "play": "Okogie STEAL (1 STL)"}, {"t": 37.57, "wp": 99.8, "hs": 96, "as": 73, "per": 4, "clock": "10:26", "play": "Crawford 1' Running Layup (2 PTS)"}, {"t": 37.83, "wp": 99.9, "hs": 99, "as": 73, "per": 4, "clock": "10:10", "play": "Murray 26' 3PT Pullup Jump Shot (25 PTS)"}, {"t": 38.08, "wp": 99.9, "hs": 99, "as": 73, "per": 4, "clock": "9:55", "play": "Valanciunas S.FOUL (P4.T2) (E.Scott)"}, {"t": 38.08, "wp": 99.9, "hs": 99, "as": 73, "per": 4, "clock": "9:55", "play": "MISS Capela Free Throw 1 of 2"}, {"t": 38.08, "wp": 99.9, "hs": 99, "as": 73, "per": 4, "clock": "9:55", "play": "Rockets Rebound"}, {"t": 38.08, "wp": 99.9, "hs": 99, "as": 74, "per": 4, "clock": "9:55", "play": "Capela Free Throw 2 of 2 (3 PTS)"}, {"t": 38.32, "wp": 99.9, "hs": 101, "as": 74, "per": 4, "clock": "9:41", "play": "Murray 20' Pullup Jump Shot (27 PTS)"}, {"t": 38.55, "wp": 99.9, "hs": 101, "as": 74, "per": 4, "clock": "9:27", "play": "MISS Holiday 13' Driving Floating Jump Shot"}, {"t": 38.58, "wp": 99.9, "hs": 101, "as": 74, "per": 4, "clock": "9:25", "play": "Capela REBOUND (Off:3 Def:0)"}, {"t": 38.63, "wp": 99.9, "hs": 101, "as": 76, "per": 4, "clock": "9:22", "play": "Capela 8' Turnaround Hook Shot (5 PTS)"}, {"t": 38.9, "wp": 99.9, "hs": 104, "as": 76, "per": 4, "clock": "9:06", "play": "Murray 27' 3PT Pullup Jump Shot (30 PTS)"}, {"t": 39.13, "wp": 100.0, "hs": 104, "as": 76, "per": 4, "clock": "8:52", "play": "Brown S.FOUL (P1.T3) (N.Sago)"}, {"t": 39.13, "wp": 99.9, "hs": 104, "as": 77, "per": 4, "clock": "8:52", "play": "Crawford Free Throw 1 of 2 (3 PTS)"}, {"t": 39.13, "wp": 99.9, "hs": 104, "as": 78, "per": 4, "clock": "8:52", "play": "Crawford Free Throw 2 of 2 (4 PTS)"}, {"t": 39.42, "wp": 99.9, "hs": 104, "as": 78, "per": 4, "clock": "8:35", "play": "MISS Brown 9' Driving Floating Jump Shot"}, {"t": 39.45, "wp": 99.9, "hs": 104, "as": 78, "per": 4, "clock": "8:33", "play": "Valanciunas REBOUND (Off:1 Def:2)"}, {"t": 39.45, "wp": 99.9, "hs": 106, "as": 78, "per": 4, "clock": "8:33", "play": "Valanciunas Tip Layup Shot (6 PTS)"}, {"t": 39.58, "wp": 100.0, "hs": 106, "as": 78, "per": 4, "clock": "8:25", "play": "MISS Crawford 26' 3PT Jump Shot"}, {"t": 39.63, "wp": 99.9, "hs": 106, "as": 78, "per": 4, "clock": "8:22", "play": "Brown REBOUND (Off:0 Def:1)"}, {"t": 39.85, "wp": 100.0, "hs": 106, "as": 78, "per": 4, "clock": "8:09", "play": "MISS Murray 27' 3PT Pullup Jump Shot"}, {"t": 39.9, "wp": 99.9, "hs": 106, "as": 78, "per": 4, "clock": "8:06", "play": "Valanciunas REBOUND (Off:2 Def:2)"}, {"t": 39.9, "wp": 100.0, "hs": 108, "as": 78, "per": 4, "clock": "8:06", "play": "Valanciunas Putback Layup (8 PTS)"}, {"t": 40.12, "wp": 100.0, "hs": 108, "as": 78, "per": 4, "clock": "7:53", "play": "MISS Sheppard 27' 3PT Jump Shot"}, {"t": 40.17, "wp": 100.0, "hs": 108, "as": 78, "per": 4, "clock": "7:50", "play": "S. Jones REBOUND (Off:0 Def:3)"}, {"t": 40.4, "wp": 100.0, "hs": 111, "as": 78, "per": 4, "clock": "7:36", "play": "Brown 24' 3PT Jump Shot (7 PTS) (Murray 4 AST)"}, {"t": 40.45, "wp": 100.0, "hs": 111, "as": 78, "per": 4, "clock": "7:33", "play": "Rockets Timeout: Regular (Reg.4 Short 0)"}, {"t": 40.45, "wp": 100.0, "hs": 111, "as": 78, "per": 4, "clock": "7:33", "play": "SUB: Strawther FOR Hardaway Jr."}, {"t": 40.45, "wp": 100.0, "hs": 111, "as": 78, "per": 4, "clock": "7:33", "play": "SUB: T. Jones FOR Murray"}, {"t": 40.45, "wp": 100.0, "hs": 111, "as": 78, "per": 4, "clock": "7:33", "play": "SUB: Green FOR Sheppard"}, {"t": 40.73, "wp": 100.0, "hs": 111, "as": 80, "per": 4, "clock": "7:16", "play": "Okogie 12' Pullup Jump Shot (6 PTS) (Holiday 1 AST)"}, {"t": 41.05, "wp": 100.0, "hs": 113, "as": 80, "per": 4, "clock": "6:57", "play": "Valanciunas Driving Dunk (10 PTS)"}, {"t": 41.35, "wp": 100.0, "hs": 113, "as": 83, "per": 4, "clock": "6:39", "play": "Okogie 26' 3PT Jump Shot (9 PTS) (Holiday 2 AST)"}, {"t": 41.72, "wp": 100.0, "hs": 115, "as": 83, "per": 4, "clock": "6:17", "play": "Valanciunas 11' Fadeaway Jumper (12 PTS)"}, {"t": 41.92, "wp": 100.0, "hs": 115, "as": 83, "per": 4, "clock": "6:05", "play": "MISS Holiday 17' Pullup Jump Shot"}, {"t": 41.95, "wp": 100.0, "hs": 115, "as": 83, "per": 4, "clock": "6:03", "play": "Valanciunas REBOUND (Off:2 Def:3)"}, {"t": 42.15, "wp": 100.0, "hs": 117, "as": 83, "per": 4, "clock": "5:51", "play": "T. Jones 8' Driving Floating Bank Jump Shot (2 PTS) (Valanciunas 3 AST)"}, {"t": 42.15, "wp": 100.0, "hs": 117, "as": 83, "per": 4, "clock": "5:51", "play": "Holiday S.FOUL (P1.T1) (N.Sago)"}, {"t": 42.15, "wp": 100.0, "hs": 117, "as": 83, "per": 4, "clock": "5:51", "play": "SUB: Nnaji FOR Brown"}, {"t": 42.15, "wp": 100.0, "hs": 117, "as": 83, "per": 4, "clock": "5:51", "play": "SUB: Roddy FOR Valanciunas"}, {"t": 42.15, "wp": 100.0, "hs": 117, "as": 83, "per": 4, "clock": "5:51", "play": "SUB: Pickett FOR S. Jones"}, {"t": 42.15, "wp": 100.0, "hs": 117, "as": 83, "per": 4, "clock": "5:51", "play": "MISS T. Jones Free Throw 1 of 1"}, {"t": 42.18, "wp": 100.0, "hs": 117, "as": 83, "per": 4, "clock": "5:49", "play": "Crawford REBOUND (Off:0 Def:1)"}, {"t": 42.33, "wp": 100.0, "hs": 117, "as": 83, "per": 4, "clock": "5:40", "play": "MISS Crawford 27' 3PT Step Back Jump Shot"}, {"t": 42.38, "wp": 100.0, "hs": 117, "as": 83, "per": 4, "clock": "5:37", "play": "Roddy REBOUND (Off:0 Def:1)"}, {"t": 42.58, "wp": 100.0, "hs": 120, "as": 83, "per": 4, "clock": "5:25", "play": "Pickett 26' 3PT Jump Shot (3 PTS) (Roddy 1 AST)"}, {"t": 42.78, "wp": 100.0, "hs": 120, "as": 83, "per": 4, "clock": "5:13", "play": "Holiday Out of Bounds - Bad Pass Turnover Turnover (P1.T15)"}, {"t": 42.93, "wp": 100.0, "hs": 120, "as": 83, "per": 4, "clock": "5:04", "play": "Nnaji OFF.Foul (P1) (C.Kirkland)"}, {"t": 42.93, "wp": 100.0, "hs": 120, "as": 83, "per": 4, "clock": "5:04", "play": "Nnaji Offensive Foul Turnover (P1.T9)"}, {"t": 43.13, "wp": 100.0, "hs": 120, "as": 85, "per": 4, "clock": "4:52", "play": "Capela 1' Alley Oop Dunk (7 PTS) (Crawford 1 AST)"}, {"t": 43.4, "wp": 100.0, "hs": 120, "as": 85, "per": 4, "clock": "4:36", "play": "MISS T. Jones 27' 3PT Step Back Jump Shot"}, {"t": 43.45, "wp": 100.0, "hs": 120, "as": 85, "per": 4, "clock": "4:33", "play": "Green REBOUND (Off:0 Def:1)"}, {"t": 43.68, "wp": 100.0, "hs": 120, "as": 85, "per": 4, "clock": "4:19", "play": "MISS Holiday 8' Driving Floating Bank Jump Shot"}, {"t": 43.7, "wp": 100.0, "hs": 120, "as": 85, "per": 4, "clock": "4:18", "play": "Holiday REBOUND (Off:1 Def:0)"}, {"t": 43.7, "wp": 100.0, "hs": 120, "as": 85, "per": 4, "clock": "4:18", "play": "MISS Holiday Tip Layup Shot"}, {"t": 43.7, "wp": 100.0, "hs": 120, "as": 85, "per": 4, "clock": "4:18", "play": "Rockets Rebound"}, {"t": 43.77, "wp": 100.0, "hs": 120, "as": 85, "per": 4, "clock": "4:14", "play": "MISS Capela 5' Layup"}, {"t": 43.8, "wp": 100.0, "hs": 120, "as": 85, "per": 4, "clock": "4:12", "play": "Capela REBOUND (Off:4 Def:0)"}, {"t": 43.8, "wp": 100.0, "hs": 120, "as": 85, "per": 4, "clock": "4:12", "play": "MISS Capela Tip Layup Shot"}, {"t": 43.8, "wp": 100.0, "hs": 120, "as": 85, "per": 4, "clock": "4:12", "play": "Crawford REBOUND (Off:1 Def:1)"}, {"t": 43.8, "wp": 100.0, "hs": 120, "as": 85, "per": 4, "clock": "4:12", "play": "MISS Crawford Tip Layup Shot"}, {"t": 43.8, "wp": 100.0, "hs": 120, "as": 85, "per": 4, "clock": "4:12", "play": "Rockets Rebound"}, {"t": 43.9, "wp": 100.0, "hs": 120, "as": 85, "per": 4, "clock": "4:06", "play": "MISS Holiday 26' 3PT Jump Shot"}, {"t": 43.93, "wp": 100.0, "hs": 120, "as": 85, "per": 4, "clock": "4:04", "play": "Roddy REBOUND (Off:0 Def:2)"}, {"t": 44.03, "wp": 100.0, "hs": 120, "as": 85, "per": 4, "clock": "3:58", "play": "MISS Pickett 26' 3PT Step Back Jump Shot"}, {"t": 44.08, "wp": 100.0, "hs": 120, "as": 85, "per": 4, "clock": "3:55", "play": "Rockets Rebound"}, {"t": 44.38, "wp": 100.0, "hs": 120, "as": 85, "per": 4, "clock": "3:37", "play": "MISS Okogie 3' Driving Reverse Layup"}, {"t": 44.4, "wp": 100.0, "hs": 120, "as": 85, "per": 4, "clock": "3:36", "play": "Strawther REBOUND (Off:0 Def:1)"}, {"t": 44.5, "wp": 100.0, "hs": 120, "as": 85, "per": 4, "clock": "3:30", "play": "MISS Nnaji 26' 3PT Running Jump Shot"}, {"t": 44.57, "wp": 100.0, "hs": 120, "as": 85, "per": 4, "clock": "3:26", "play": "Okogie REBOUND (Off:1 Def:1)"}, {"t": 44.67, "wp": 100.0, "hs": 120, "as": 85, "per": 4, "clock": "3:20", "play": "MISS Green 26' 3PT Jump Shot"}, {"t": 44.7, "wp": 100.0, "hs": 120, "as": 85, "per": 4, "clock": "3:18", "play": "Nnaji REBOUND (Off:0 Def:1)"}, {"t": 44.95, "wp": 100.0, "hs": 120, "as": 85, "per": 4, "clock": "3:03", "play": "MISS Nnaji 22' Jump Shot"}, {"t": 44.98, "wp": 100.0, "hs": 120, "as": 85, "per": 4, "clock": "3:01", "play": "Roddy REBOUND (Off:1 Def:2)"}, {"t": 45.05, "wp": 100.0, "hs": 120, "as": 85, "per": 4, "clock": "2:57", "play": "MISS Roddy 24' 3PT Fadeaway Jumper"}, {"t": 45.1, "wp": 100.0, "hs": 120, "as": 85, "per": 4, "clock": "2:54", "play": "Capela REBOUND (Off:4 Def:1)"}, {"t": 45.23, "wp": 100.0, "hs": 120, "as": 85, "per": 4, "clock": "2:46", "play": "MISS Holiday 26' 3PT Pullup Jump Shot"}, {"t": 45.25, "wp": 100.0, "hs": 120, "as": 85, "per": 4, "clock": "2:45", "play": "Rockets Rebound"}, {"t": 45.25, "wp": 100.0, "hs": 120, "as": 85, "per": 4, "clock": "2:45", "play": "Pickett L.B.FOUL (P1.T4) (C.Kirkland)"}, {"t": 45.25, "wp": 100.0, "hs": 120, "as": 85, "per": 4, "clock": "2:45", "play": "NUGGETS Timeout: Regular (Full 4 Short 0)"}, {"t": 45.47, "wp": 100.0, "hs": 120, "as": 85, "per": 4, "clock": "2:32", "play": "MISS Green 26' 3PT Jump Shot"}, {"t": 45.47, "wp": 100.0, "hs": 120, "as": 85, "per": 4, "clock": "2:32", "play": "NUGGETS Rebound"}, {"t": 45.65, "wp": 100.0, "hs": 123, "as": 85, "per": 4, "clock": "2:21", "play": "Strawther 28' 3PT Step Back Jump Shot (3 PTS) (T. Jones 1 AST)"}, {"t": 45.9, "wp": 100.0, "hs": 123, "as": 85, "per": 4, "clock": "2:06", "play": "MISS Green 24' 3PT Jump Shot"}, {"t": 45.95, "wp": 100.0, "hs": 123, "as": 85, "per": 4, "clock": "2:03", "play": "Okogie REBOUND (Off:2 Def:1)"}, {"t": 45.98, "wp": 100.0, "hs": 123, "as": 87, "per": 4, "clock": "2:01", "play": "Capela 1' Dunk (9 PTS) (Okogie 3 AST)"}, {"t": 46.28, "wp": 100.0, "hs": 123, "as": 87, "per": 4, "clock": "1:43", "play": "MISS Strawther 6' Driving Bank Hook Shot"}, {"t": 46.32, "wp": 100.0, "hs": 123, "as": 87, "per": 4, "clock": "1:41", "play": "Crawford REBOUND (Off:1 Def:2)"}, {"t": 46.4, "wp": 100.0, "hs": 123, "as": 87, "per": 4, "clock": "1:36", "play": "MISS Crawford 3' Running Reverse Layup"}, {"t": 46.43, "wp": 100.0, "hs": 123, "as": 87, "per": 4, "clock": "1:34", "play": "Capela REBOUND (Off:5 Def:1)"}, {"t": 46.43, "wp": 100.0, "hs": 123, "as": 87, "per": 4, "clock": "1:34", "play": "MISS Capela Tip Layup Shot"}, {"t": 46.45, "wp": 100.0, "hs": 123, "as": 87, "per": 4, "clock": "1:33", "play": "Capela REBOUND (Off:6 Def:1)"}, {"t": 46.47, "wp": 100.0, "hs": 123, "as": 87, "per": 4, "clock": "1:32", "play": "Capela Lost Ball Turnover (P2.T16)"}, {"t": 46.47, "wp": 100.0, "hs": 123, "as": 87, "per": 4, "clock": "1:32", "play": "Nnaji STEAL (1 STL)"}, {"t": 46.53, "wp": 100.0, "hs": 123, "as": 87, "per": 4, "clock": "1:28", "play": "Holiday S.FOUL (P2.T2) (C.Kirkland)"}, {"t": 46.53, "wp": 100.0, "hs": 123, "as": 87, "per": 4, "clock": "1:28", "play": "MISS Nnaji Free Throw 1 of 2"}, {"t": 46.53, "wp": 100.0, "hs": 123, "as": 87, "per": 4, "clock": "1:28", "play": "NUGGETS Rebound"}, {"t": 46.53, "wp": 100.0, "hs": 124, "as": 87, "per": 4, "clock": "1:28", "play": "Nnaji Free Throw 2 of 2 (1 PTS)"}, {"t": 46.78, "wp": 100.0, "hs": 124, "as": 89, "per": 4, "clock": "1:13", "play": "Holiday 8' Driving Floating Jump Shot (2 PTS)"}, {"t": 46.95, "wp": 100.0, "hs": 127, "as": 89, "per": 4, "clock": "1:03", "play": "Strawther 26' 3PT Jump Shot (6 PTS) (T. Jones 2 AST)"}, {"t": 47.15, "wp": 100.0, "hs": 127, "as": 89, "per": 4, "clock": "0:51", "play": "MISS Okogie 3PT Jump Shot"}, {"t": 47.17, "wp": 100.0, "hs": 127, "as": 89, "per": 4, "clock": "0:50", "play": "Rockets Rebound"}, {"t": 47.17, "wp": 100.0, "hs": 127, "as": 89, "per": 4, "clock": "0:50", "play": "Roddy L.B.FOUL (P1.PN) (N.Sago)"}, {"t": 47.17, "wp": 100.0, "hs": 127, "as": 90, "per": 4, "clock": "0:50", "play": "Crawford Free Throw 1 of 2 (5 PTS)"}, {"t": 47.17, "wp": 100.0, "hs": 127, "as": 90, "per": 4, "clock": "0:50", "play": "MISS Crawford Free Throw 2 of 2"}, {"t": 47.2, "wp": 100.0, "hs": 127, "as": 90, "per": 4, "clock": "0:48", "play": "Okogie REBOUND (Off:3 Def:1)"}, {"t": 47.2, "wp": 100.0, "hs": 127, "as": 90, "per": 4, "clock": "0:48", "play": "MISS Okogie 2' Tip Layup Shot"}, {"t": 47.23, "wp": 100.0, "hs": 127, "as": 90, "per": 4, "clock": "0:46", "play": "Roddy REBOUND (Off:1 Def:3)"}, {"t": 47.35, "wp": 100.0, "hs": 127, "as": 90, "per": 4, "clock": "0:39", "play": "Capela S.FOUL (P2.PN) (E.Scott)"}, {"t": 47.35, "wp": 100.0, "hs": 128, "as": 90, "per": 4, "clock": "0:39", "play": "Roddy Free Throw 1 of 2 (1 PTS)"}, {"t": 47.35, "wp": 100.0, "hs": 129, "as": 90, "per": 4, "clock": "0:39", "play": "Roddy Free Throw 2 of 2 (2 PTS)"}, {"t": 47.53, "wp": 100.0, "hs": 129, "as": 93, "per": 4, "clock": "0:28", "play": "Okogie 26' 3PT Jump Shot (12 PTS) (Holiday 3 AST)"}, {"t": 47.95, "wp": 100.0, "hs": 129, "as": 93, "per": 4, "clock": "0:03", "play": "NUGGETS Turnover: Shot Clock (T#10)"}, {"t": 48.0, "wp": 100.0, "hs": 129, "as": 93, "per": 4, "clock": "0:00", "play": "ROCKETS Heave"}, {"t": 48.0, "wp": 100.0, "hs": 129, "as": 93, "per": 4, "clock": "0:00", "play": "Rockets Rebound"}, {"t": 48.0, "wp": 100.0, "hs": 129, "as": 93, "per": 4, "clock": "0:00", "play": "End of 4th Period (12:24 AM EST)"}], "turningPoints": [{"per": 2, "clock": "0:02", "player": "Braun", "team": "DEN", "play": "Braun 31' 3PT Step Back Jump Shot (13 PTS) (Gordon 1 AST)", "before": 71.4, "after": 84.3, "swing": 12.9}, {"per": 2, "clock": "2:48", "player": "Braun", "team": "DEN", "play": "Braun 1' Driving Layup (6 PTS) (Jokic 7 AST)", "before": 47.9, "after": 59.5, "swing": 11.6}, {"per": 2, "clock": "3:30", "player": "Thompson", "team": "HOU", "play": "Thompson 2' Dunk (8 PTS) (Okogie 2 AST)", "before": 59.3, "after": 48.0, "swing": -11.3}, {"per": 3, "clock": "9:20", "player": "Johnson", "team": "DEN", "play": "Johnson 3PT Running Jump Shot (10 PTS) (Jokic 10 AST)", "before": 77.6, "after": 88.8, "swing": 11.2}, {"per": 2, "clock": "2:26", "player": "Johnson", "team": "DEN", "play": "Johnson 3' Running Layup (7 PTS) (Hardaway Jr. 1 AST)", "before": 59.6, "after": 70.3, "swing": 10.7}, {"per": 2, "clock": "4:05", "player": "Thompson", "team": "HOU", "play": "Thompson 4' Layup (6 PTS) (Okogie 1 AST)", "before": 69.4, "after": 59.3, "swing": -10.1}], "players": [{"name": "Murray", "team": "DEN", "personId": 1627750, "impact": 60.51, "net": 59.67, "events": 35}, {"name": "Braun", "team": "DEN", "personId": 1631128, "impact": 54.27, "net": 54.13, "events": 16}, {"name": "Thompson", "team": "HOU", "personId": 1641708, "impact": 47.05, "net": -46.33, "events": 28}, {"name": "Johnson", "team": "DEN", "personId": 1629661, "impact": 44.76, "net": 44.58, "events": 19}, {"name": "Joki\u0107", "team": "DEN", "personId": 203999, "impact": 42.95, "net": 42.87, "events": 45}, {"name": "Sengun", "team": "HOU", "personId": 1630578, "impact": 36.68, "net": -35.96, "events": 24}, {"name": "Eason", "team": "HOU", "personId": 1631106, "impact": 29.49, "net": -27.81, "events": 24}, {"name": "Smith Jr.", "team": "HOU", "personId": 1631095, "impact": 28.59, "net": -27.75, "events": 27}, {"name": "Hardaway Jr.", "team": "DEN", "personId": 203501, "impact": 26.67, "net": 26.51, "events": 18}, {"name": "Durant", "team": "HOU", "personId": 201142, "impact": 24.87, "net": -23.59, "events": 20}, {"name": "Sheppard", "team": "HOU", "personId": 1642263, "impact": 20.11, "net": -18.57, "events": 24}, {"name": "Valan\u010di\u016bnas", "team": "DEN", "personId": 202685, "impact": 16.34, "net": 16.34, "events": 17}], "insights": {"Game Drama Score": {"value": "50", "details": "Drama score 50/100: final margin 36, 3 lead changes, 17 tied states, 5 major WP swings, losing team max WP 57.1%, max deficit overcome 5, peak clutch pressure 77.0."}, "Most Valuable Play": {"value": "Hardaway Jr. 27' 3PT Jump Shot (6 PTS) (Murray 2 AST)", "details": "Q2, 10:41, DEN - Hardaway Jr.: Hardaway Jr. 27' 3PT Jump Shot (6 PTS) (Murray 2 AST) (+12.9 WP points)"}, "Most Damaging Play": {"value": "Braun 1' Driving Layup (6 PTS) (Jokic 7 AST)", "details": "Q2, 2:48, DEN - Braun: Braun 1' Driving Layup (6 PTS) (Jokic 7 AST) (-11.3 WP points)"}, "Clutch-Time Scoring Summary": {"value": "Final 5 minutes of 4Q/OT scoring: Home 9, Away 10.", "details": "Strawther (DEN) 6 pts"}}, "recap": {"Final Result": "HOU beat DEN 129-93 by 36 points.", "Biggest Turning Point": "The game's sharpest probability swing came at **Q2, 0:02.2**, when home win probability moved from **71.4%** to **84.3%** (**+12.9 percentage points**). Key play:** Braun 31' 3PT Step Back Jump Shot (13 PTS) (Gordon 1 AST)", "Player Impact": "Murray (DEN)** led the player-impact table with **60.5 total win-probability impact points** across **35 tracked events**.", "Comeback Reality": "The most interesting comeback window came at **Q4, 0:39.1**. **Away** trailed by **39 points** with an estimated comeback chance of **0.0%**, which ClutchCast labeled **Nearly impossible**.", "Hidden Momentum": "The strongest hidden-momentum reading came at **Q1, 7:24**, with a score of **93.4** and a label of **Strong home momentum**. Momentum play:** Murray 1' Cutting Dunk Shot (2 PTS) (Jokic 2 AST)", "Model Note": "ClutchCast selects its champion model using probability-quality metrics: Brier score first, then log loss, ROC-AUC, and accuracy. The recap uses the champion prediction file when available."}}